easy_logs/__init__.py
easy_logs/_configurations.py
easy_logs/_logging_utils.py
easy_logs/main.py
easy_logs-1.1.2.dist-info/METADATA
easy_logs-1.1.2.dist-info/WHEEL
easy_logs-1.1.2.dist-info/top_level.txt
easy_logs-1.1.2.dist-info/RECORD
