Metadata-Version: 2.1
Name: easy-logs
Version: 1.1.2
Summary: package for easy colored logs with predefined configurations.
Home-page: https://github.com/michalskibinski109/easy_logging
Author: Michał Skibiński
Author-email: mskibinski109@gmail.com
Classifier: Programming Language :: Python :: 3
Classifier: License :: OSI Approved :: MIT License
Classifier: Operating System :: OS Independent
Requires-Python: >=3.8
